anglerfish/__init__.py
anglerfish/bytes2human.py
anglerfish/check_encoding.py
anglerfish/check_folder.py
anglerfish/check_hardware.py
anglerfish/exceptions.py
anglerfish/get_clipboard.py
anglerfish/get_free_port.py
anglerfish/get_human_datetime.py
anglerfish/get_pdb_on_exception.py
anglerfish/get_public_ip.py
anglerfish/get_random_font.py
anglerfish/get_random_pastel_color.py
anglerfish/get_temp_folder.py
anglerfish/html2ebook.py
anglerfish/json2xml.py
anglerfish/make_async.py
anglerfish/make_autochecksum.py
anglerfish/make_beep.py
anglerfish/make_chainable_future.py
anglerfish/make_datauri.py
anglerfish/make_json_flat.py
anglerfish/make_json_pretty.py
anglerfish/make_log_exception.py
anglerfish/make_multiprocess.py
anglerfish/make_multithread.py
anglerfish/make_notification.py
anglerfish/make_postexec_message.py
anglerfish/make_retry.py
anglerfish/make_template_python.py
anglerfish/make_test_terminal_color.py
anglerfish/make_typecheck.py
anglerfish/make_watch.py
anglerfish/make_zip_comment.py
anglerfish/number2currency.py
anglerfish/path2import.py
anglerfish/seconds2human.py
anglerfish/set_desktop_launcher.py
anglerfish/set_display_off.py
anglerfish/set_process_name.py
anglerfish/set_process_priority.py
anglerfish/set_single_instance.py
anglerfish/set_terminal_title.py
anglerfish/stealth2string.py
anglerfish/string2stealth.py
anglerfish/url2path.py
anglerfish/walk2dict.py
anglerfish/walk2list.py
anglerfish-2.5.0.dist-info/DESCRIPTION.rst
anglerfish-2.5.0.dist-info/METADATA
anglerfish-2.5.0.dist-info/RECORD
anglerfish-2.5.0.dist-info/WHEEL
anglerfish-2.5.0.dist-info/metadata.json
anglerfish-2.5.0.dist-info/top_level.txt
anglerfish-2.5.0.dist-info/zip-safe
